tornado_elasticsearch.py
tornado_elasticsearch-0.5.0.dist-info/DESCRIPTION.rst
tornado_elasticsearch-0.5.0.dist-info/METADATA
tornado_elasticsearch-0.5.0.dist-info/metadata.json
tornado_elasticsearch-0.5.0.dist-info/RECORD
tornado_elasticsearch-0.5.0.dist-info/top_level.txt
tornado_elasticsearch-0.5.0.dist-info/WHEEL
tornado_elasticsearch-0.5.0.dist-info/zip-safe
