Metadata-Version: 2.0
Name: tornado-elasticsearch
Version: 0.5.0
Summary: Extends the official Elasticsearch Python API adding Tornado AsyncHTTPClient support
Home-page: https://github.com/gmr/tornado_elasticsearch
Author: Gavin M. Roy
Author-email: gavinmroy@gmail.com
License: BSD
Platform: UNKNOWN
Classifier: Development Status :: 3 - Alpha
Classifier: Intended Audience :: Developers
Classifier: License :: OSI Approved :: BSD License
Classifier: Operating System :: OS Independent
Classifier: Programming Language :: Python :: 2
Classifier: Programming Language :: Python :: 2.6
Classifier: Programming Language :: Python :: 2.7
Classifier: Programming Language :: Python :: 3
Classifier: Programming Language :: Python :: 3.2
Classifier: Programming Language :: Python :: 3.3
Classifier: Programming Language :: Python :: Implementation :: CPython
Classifier: Programming Language :: Python :: Implementation :: PyPy
Classifier: Topic :: Communications
Classifier: Topic :: Internet
Classifier: Topic :: Software Development :: Libraries
Requires-Dist: elasticsearch
Requires-Dist: tornado
